LICENSE
MANIFEST.in
README.md
requirements.txt
setup.py
pikudhaoref/__init__.py
pikudhaoref/abc.py
pikudhaoref/base.py
pikudhaoref/city.py
pikudhaoref/client.py
pikudhaoref/enums.py
pikudhaoref/exceptions.py
pikudhaoref/http.py
pikudhaoref/range.py
pikudhaoref/siren.py
pikudhaoref/utils.py
pikudhaoref.py.egg-info/PKG-INFO
pikudhaoref.py.egg-info/SOURCES.txt
pikudhaoref.py.egg-info/dependency_links.txt
pikudhaoref.py.egg-info/requires.txt
pikudhaoref.py.egg-info/top_level.txt