Metadata-Version: 2.1
Name: pikudhaoref.py
Version: 0.0.8
Summary: An API wrapper for Pikud Haoref's rocket API.
Home-page: https://github.com/adam757521/PikudHaoref.py
Author: adam7100
License: MIT
Download-URL: https://github.com/adam757521/PikudHaoref.py/archive/refs/tags/v0.0.8.tar.gz
Keywords: rocket,siren,pikudhaoref,api,wrapper,python
Platform: UNKNOWN
Classifier: Development Status :: 4 - Beta
Classifier: Intended Audience :: Developers
Classifier: Topic :: Software Development :: Build Tools
Classifier: License :: OSI Approved :: MIT License
Classifier: Programming Language :: Python :: 3
Classifier: Programming Language :: Python :: 3.4
Classifier: Programming Language :: Python :: 3.5
Classifier: Programming Language :: Python :: 3.6
